[
{"MS_NR": 100, "MS_DESC": "???? ????? Lisec GFB ??", "CALENDAR_NR": 1008, "BUFER": 6, "id": 1},
{"MS_NR": 102, "MS_DESC": "???? ????? Lisec ESL ??", "CALENDAR_NR": 1028, "BUFER": 6, "id": 2},
{"MS_NR": 103, "MS_DESC": "Dynopt_LowE", "CALENDAR_NR": 1038, "BUFER": 0, "id": 3},
{"MS_NR": 104, "MS_DESC": "Dynopt_Multi", "CALENDAR_NR": 1048, "BUFER": 0, "id": 4},
{"MS_NR": 105, "MS_DESC": "Dynopt_A", "CALENDAR_NR": 1058, "BUFER": 0, "id": 5},
{"MS_NR": 201, "MS_DESC": "Busetti2200", "CALENDAR_NR": 20114, "BUFER": 0, "id": 6},
{"MS_NR": 211, "MS_DESC": "Master edge", "CALENDAR_NR": 21115, "BUFER": 0, "id": 7},
{"MS_NR": 212, "MS_DESC": "MASTER 23", "CALENDAR_NR": 21216, "BUFER": 0, "id": 8},
{"MS_NR": 213, "MS_DESC": "MASTER 43", "CALENDAR_NR": 21356, "BUFER": 7, "id": 9},
{"MS_NR": 240, "MS_DESC": "GlassJet", "CALENDAR_NR": 24050, "BUFER": 8, "id": 10},
{"MS_NR": 241, "MS_DESC": "Fleischle2", "CALENDAR_NR": 2413, "BUFER": 0, "id": 11},
{"MS_NR": 242, "MS_DESC": "Ino Ziri (????)", "CALENDAR_NR": 24224, "BUFER": 25, "id": 12},
{"MS_NR": 243, "MS_DESC": "????????", "CALENDAR_NR": 24325, "BUFER": 11, "id": 13},
{"MS_NR": 247, "MS_DESC": "GlassLine", "CALENDAR_NR": 24783, "BUFER": 12, "id": 14},
{"MS_NR": 248, "MS_DESC": "Rollmac Jumbo", "CALENDAR_NR": 248225, "BUFER": 12, "id": 15},
{"MS_NR": 250, "MS_DESC": "Tamglass HTF PROe", "CALENDAR_NR": 2507, "BUFER": 6, "id": 16},
{"MS_NR": 270, "MS_DESC": "North Glass", "CALENDAR_NR": 27011, "BUFER": 6, "id": 17},
{"MS_NR": 290, "MS_DESC": "EVA???", "CALENDAR_NR": 29029, "BUFER": 12, "id": 18},
{"MS_NR": 300, "MS_DESC": "LAM Line Tamglass", "CALENDAR_NR": 90005, "BUFER": 10, "id": 19},
{"MS_NR": 301, "MS_DESC": "LAM Line Tamglass Common", "CALENDAR_NR": 90005, "BUFER": 0, "id": 20},
{"MS_NR": 302, "MS_DESC": "???????? Tamglass", "CALENDAR_NR": 90006, "BUFER": 0, "id": 21},
{"MS_NR": 303, "MS_DESC": "???????????? ????????", "CALENDAR_NR": 303310, "BUFER": 0, "id": 22},
{"MS_NR": 310, "MS_DESC": "LAM Line Lisec", "CALENDAR_NR": 31010, "BUFER": 12, "id": 23},
{"MS_NR": 312, "MS_DESC": "???????? Italmatic", "CALENDAR_NR": 90006, "BUFER": 10, "id": 24},
{"MS_NR": 320, "MS_DESC": "LAM Line Lisec3300", "CALENDAR_NR": 90005, "BUFER": 10, "id": 25},
{"MS_NR": 322, "MS_DESC": "???????? Akarmak 6", "CALENDAR_NR": 90006, "BUFER": 0, "id": 26},
{"MS_NR": 323, "MS_DESC": "???????? Akarmak 12", "CALENDAR_NR": 90006, "BUFER": 0, "id": 27},
{"MS_NR": 325, "MS_DESC": "LAM Line Benteller 3312", "CALENDAR_NR": 90005, "BUFER": 10, "id": 28},
{"MS_NR": 340, "MS_DESC": "?? ???????(C?)", "CALENDAR_NR": 34019, "BUFER": 18, "id": 29},
{"MS_NR": 350, "MS_DESC": "???????-?????????", "CALENDAR_NR": 35019, "BUFER": 0, "id": 30},
{"MS_NR": 400, "MS_DESC": "Manual Frame Cutting", "CALENDAR_NR": 40020, "BUFER": 0, "id": 31},
{"MS_NR": 500, "MS_DESC": "LENHARDT-???", "CALENDAR_NR": 50021, "BUFER": 12, "id": 32},
{"MS_NR": 501, "MS_DESC": "manual IG-Line", "CALENDAR_NR": 50137, "BUFER": 12, "id": 33},
{"MS_NR": 502, "MS_DESC": "manual IG-Line(Window)", "CALENDAR_NR": 50221, "BUFER": 0, "id": 34},
{"MS_NR": 510, "MS_DESC": "LENHARDT-?????", "CALENDAR_NR": 51021, "BUFER": 12, "id": 35},
{"MS_NR": 515, "MS_DESC": "Lisec-??????????", "CALENDAR_NR": 51521, "BUFER": 0, "id": 36},
{"MS_NR": 550, "MS_DESC": "SprIG", "CALENDAR_NR": 5508, "BUFER": 0, "id": 37},
{"MS_NR": 600, "MS_DESC": "???????? ???. ??", "CALENDAR_NR": 60043, "BUFER": 0, "id": 38},
{"MS_NR": 601, "MS_DESC": "??????????", "CALENDAR_NR": 6011, "BUFER": 0, "id": 39},
{"MS_NR": 602, "MS_DESC": "????? Tenon", "CALENDAR_NR": 90007, "BUFER": 2, "id": 40},
{"MS_NR": 603, "MS_DESC": "?????????? ???", "CALENDAR_NR": 6031, "BUFER": 0, "id": 41},
{"MS_NR": 604, "MS_DESC": "????? Lisec", "CALENDAR_NR": 90007, "BUFER": 24, "id": 42},
{"MS_NR": 605, "MS_DESC": "???????????", "CALENDAR_NR": 6051, "BUFER": 0, "id": 43},
{"MS_NR": 700, "MS_DESC": "LOADING WINDOW", "CALENDAR_NR": 70045, "BUFER": 0, "id": 44},
{"MS_NR": 730, "MS_DESC": "UF-?????? (????????)", "CALENDAR_NR": 7305, "BUFER": 0, "id": 45},
{"MS_NR": 800, "MS_DESC": "?????????????????", "CALENDAR_NR": 8006, "BUFER": 0, "id": 46},
{"MS_NR": 801, "MS_DESC": "?????? ????????", "CALENDAR_NR": 8016, "BUFER": 0, "id": 47},
{"MS_NR": 806, "MS_DESC": "?????????????? GDS/ULSP", "CALENDAR_NR": 80612, "BUFER": 18, "id": 48},
{"MS_NR": 900, "MS_DESC": "PUTSCH MEN", "CALENDAR_NR": 90040, "BUFER": 0, "id": 49},
{"MS_NR": 1000, "MS_DESC": "Lisec ESL M1 Blue", "CALENDAR_NR": 90001, "BUFER": 6, "id": 50},
{"MS_NR": 1001, "MS_DESC": "Lisec ESL M1 Red", "CALENDAR_NR": 90001, "BUFER": 6, "id": 51},
{"MS_NR": 1002, "MS_DESC": "Lisec GFB-VB", "CALENDAR_NR": 100258, "BUFER": 6, "id": 52},
{"MS_NR": 1004, "MS_DESC": "Lisec GFB M2 ???????", "CALENDAR_NR": 100459, "BUFER": 6, "id": 53},
{"MS_NR": 1005, "MS_DESC": "Hegla Galactic 1233", "CALENDAR_NR": 100569, "BUFER": 6, "id": 54},
{"MS_NR": 1050, "MS_DESC": "HEGLA2 M1 Blue", "CALENDAR_NR": 90001, "BUFER": 6, "id": 55},
{"MS_NR": 1051, "MS_DESC": "HEGLA1 M1 Red", "CALENDAR_NR": 90001, "BUFER": 6, "id": 56},
{"MS_NR": 1500, "MS_DESC": "TORGAUER ?????????", "CALENDAR_NR": 90010, "BUFER": 15, "id": 57},
{"MS_NR": 1501, "MS_DESC": "TORGAUER ????????", "CALENDAR_NR": 90009, "BUFER": 12, "id": 58},
{"MS_NR": 1502, "MS_DESC": "TORGAUER 2 ?????????", "CALENDAR_NR": 90010, "BUFER": 15, "id": 59},
{"MS_NR": 1503, "MS_DESC": "TORGAUER 2 ????????", "CALENDAR_NR": 90009, "BUFER": 12, "id": 60},
{"MS_NR": 1504, "MS_DESC": "TORGAUER jumbo ?????????", "CALENDAR_NR": 90010, "BUFER": 15, "id": 61},
{"MS_NR": 1505, "MS_DESC": "TORGAUER jumbo ????????", "CALENDAR_NR": 90009, "BUFER": 12, "id": 62},
{"MS_NR": 1506, "MS_DESC": "TORGAUER 12m ?????????", "CALENDAR_NR": 90010, "BUFER": 15, "id": 63},
{"MS_NR": 1507, "MS_DESC": "TORGAUER 12m ????????", "CALENDAR_NR": 90009, "BUFER": 12, "id": 64},
{"MS_NR": 1600, "MS_DESC": "Pujol ?????????", "CALENDAR_NR": 90010, "BUFER": 15, "id": 65},
{"MS_NR": 1601, "MS_DESC": "Pujol ????????", "CALENDAR_NR": 90009, "BUFER": 12, "id": 66},
{"MS_NR": 1700, "MS_DESC": "????????? ????????", "CALENDAR_NR": 17001700, "BUFER": 24, "id": 67},
{"MS_NR": 2010, "MS_DESC": "Busetti3300", "CALENDAR_NR": 201034, "BUFER": 0, "id": 68},
{"MS_NR": 2020, "MS_DESC": "Benteler", "CALENDAR_NR": 2020134, "BUFER": 6, "id": 69},
{"MS_NR": 2050, "MS_DESC": "FOREL32", "CALENDAR_NR": 90003, "BUFER": 5, "id": 70},
{"MS_NR": 2060, "MS_DESC": "FOREL 2 (?????. ????)", "CALENDAR_NR": 206028, "BUFER": 6, "id": 71},
{"MS_NR": 2110, "MS_DESC": "FORVET3300", "CALENDAR_NR": 211034, "BUFER": 0, "id": 72},
{"MS_NR": 2120, "MS_DESC": "MASTER 23-2", "CALENDAR_NR": 2120160, "BUFER": 0, "id": 73},
{"MS_NR": 2150, "MS_DESC": "FOREL 1", "CALENDAR_NR": 90003, "BUFER": 5, "id": 74},
{"MS_NR": 2151, "MS_DESC": "FOREL Common", "CALENDAR_NR": 215161, "BUFER": 0, "id": 75},
{"MS_NR": 2160, "MS_DESC": "FOREL 25-3", "CALENDAR_NR": 90003, "BUFER": 5, "id": 76},
{"MS_NR": 2170, "MS_DESC": "KBF-60/33", "CALENDAR_NR": 90004, "BUFER": 6, "id": 77},
{"MS_NR": 2171, "MS_DESC": "KBF-Common", "CALENDAR_NR": 90004, "BUFER": 0, "id": 78},
{"MS_NR": 2201, "MS_DESC": "Benteller12-1", "CALENDAR_NR": 90002, "BUFER": 0, "id": 79},
{"MS_NR": 2202, "MS_DESC": "Benteller12-2", "CALENDAR_NR": 90002, "BUFER": 0, "id": 80},
{"MS_NR": 2203, "MS_DESC": "Systron", "CALENDAR_NR": 90004, "BUFER": 6, "id": 81},
{"MS_NR": 2500, "MS_DESC": "Magnum", "CALENDAR_NR": 90008, "BUFER": 6, "id": 82},
{"MS_NR": 2510, "MS_DESC": "Magnum(?? ???)", "CALENDAR_NR": 251080, "BUFER": 0, "id": 83},
{"MS_NR": 2520, "MS_DESC": "Robotemp ???????", "CALENDAR_NR": 90008, "BUFER": 6, "id": 84},
{"MS_NR": 2530, "MS_DESC": "North Glass 6", "CALENDAR_NR": 90008, "BUFER": 6, "id": 85},
{"MS_NR": 2540, "MS_DESC": "North Glass 12", "CALENDAR_NR": 90008, "BUFER": 6, "id": 86},
{"MS_NR": 3500, "MS_DESC": "?????? ????", "CALENDAR_NR": 3500410, "BUFER": 6, "id": 87},
{"MS_NR": 3510, "MS_DESC": "?????? ????", "CALENDAR_NR": 351041, "BUFER": 6, "id": 88},
{"MS_NR": 4000, "MS_DESC": "BSV", "CALENDAR_NR": 400032, "BUFER": 0, "id": 89},
{"MS_NR": 5000, "MS_DESC": "LisecROBOT", "CALENDAR_NR": 500031, "BUFER": 0, "id": 90},
{"MS_NR": 5050, "MS_DESC": "LisecIG New", "CALENDAR_NR": 505030, "BUFER": 10, "id": 91},
{"MS_NR": 5051, "MS_DESC": "LisecIG 120/33", "CALENDAR_NR": 5051130, "BUFER": 10, "id": 92},
{"MS_NR": 5100, "MS_DESC": "Bystronic", "CALENDAR_NR": 510033, "BUFER": 18, "id": 93},
{"MS_NR": 5400, "MS_DESC": "Control", "CALENDAR_NR": 90011, "BUFER": 0, "id": 94},
{"MS_NR": 5401, "MS_DESC": "Control Pyropane", "CALENDAR_NR": 90011, "BUFER": 0, "id": 95},
{"MS_NR": 5500, "MS_DESC": "Box", "CALENDAR_NR": 550043, "BUFER": 0, "id": 96},
{"MS_NR": 5800, "MS_DESC": "PackingIG", "CALENDAR_NR": 580043, "BUFER": 6, "id": 97},
{"MS_NR": 5900, "MS_DESC": "PackingSG", "CALENDAR_NR": 590043, "BUFER": 6, "id": 98},
{"MS_NR": 6000, "MS_DESC": "?????? ????????", "CALENDAR_NR": 90012, "BUFER": 6, "id": 99},
{"MS_NR": 6500, "MS_DESC": "???????? ?????????", "CALENDAR_NR": 90012, "BUFER": 6, "id": 100},
{"MS_NR": 7000, "MS_DESC": "LOADING", "CALENDAR_NR": 700049, "BUFER": 0, "id": 101},
{}]